gadfastemporal/__init__.py
gadfastemporal/temporal.py
gadfastemporal/workflows.py
gadfastemporal/converters/__init__.py
gadfastemporal/converters/pydantic.py
gadfastemporal/decorators/__init__.py
gadfastemporal/decorators/activities.py
gadfastemporal/decorators/workflows.py
gadfastemporal/enums/__init__.py
gadfastemporal/enums/policies.py
gadfastemporal/executors/__init__.py
gadfastemporal/executors/activities.py
gadfastemporal/executors/workflows.py
gadfastemporal/interceptors/__init__.py
gadfastemporal/interceptors/clients/__init__.py
gadfastemporal/interceptors/clients/context.py
gadfastemporal/interceptors/workers/__init__.py
gadfastemporal/interceptors/workers/sentry.py
gadfastemporal/policies/__init__.py
gadfastemporal/policies/activities.py
gadfastemporal/policies/workflows.py
gadfastemporal/typings/__init__.py
gadfastemporal/typings/classes.py
gadfastemporal/typings/function.py
tests/__init__.py
tests/test_init.py
gadfastemporal-0.0.1.dist-info/LICENSE
gadfastemporal-0.0.1.dist-info/METADATA
gadfastemporal-0.0.1.dist-info/WHEEL
gadfastemporal-0.0.1.dist-info/top_level.txt
gadfastemporal-0.0.1.dist-info/RECORD
