Metadata-Version: 2.1
Name: gadfastemporal
Version: 0.0.1
Summary: Example repository demonstrating integration of Temporal workflows with FastAPI.
Home-page: https://github.com/AlexDemure/gadfastemporal
Author: Alexander Grishchenko
Author-email: alexanderdemure@gmail.com
Classifier: Programming Language :: Python :: 3
Classifier: License :: OSI Approved :: MIT License
Classifier: Operating System :: OS Independent
Requires-Python: >=3.8
License-File: LICENSE
Requires-Dist: sentry-sdk
Requires-Dist: temporalio
